supabase_pydantic/__init__.py
supabase_pydantic/__main__.py
supabase_pydantic/cli/__init__.py
supabase_pydantic/cli/commands/__init__.py
supabase_pydantic/cli/commands/clean.py
supabase_pydantic/cli/commands/gen.py
supabase_pydantic/cli/common.py
supabase_pydantic/core/__init__.py
supabase_pydantic/core/config.py
supabase_pydantic/core/constants.py
supabase_pydantic/core/models.py
supabase_pydantic/core/writers/__init__.py
supabase_pydantic/core/writers/abstract.py
supabase_pydantic/core/writers/factories.py
supabase_pydantic/core/writers/pydantic.py
supabase_pydantic/core/writers/sqlalchemy.py
supabase_pydantic/core/writers/utils.py
supabase_pydantic/db/__init__.py
supabase_pydantic/db/abstract/__init__.py
supabase_pydantic/db/abstract/base_connector.py
supabase_pydantic/db/abstract/base_schema_reader.py
supabase_pydantic/db/builder.py
supabase_pydantic/db/connection.py
supabase_pydantic/db/connection_manager.py
supabase_pydantic/db/connectors/__init__.py
supabase_pydantic/db/connectors/mysql/__init__.py
supabase_pydantic/db/connectors/mysql/connector.py
supabase_pydantic/db/connectors/mysql/schema_reader.py
supabase_pydantic/db/connectors/postgres/__init__.py
supabase_pydantic/db/connectors/postgres/connector.py
supabase_pydantic/db/connectors/postgres/schema_reader.py
supabase_pydantic/db/constants.py
supabase_pydantic/db/database_type.py
supabase_pydantic/db/drivers/__init__.py
supabase_pydantic/db/drivers/mysql/__init__.py
supabase_pydantic/db/drivers/mysql/constants.py
supabase_pydantic/db/drivers/mysql/queries.py
supabase_pydantic/db/drivers/mysql/type_maps.py
supabase_pydantic/db/drivers/postgres/__init__.py
supabase_pydantic/db/drivers/postgres/constants.py
supabase_pydantic/db/drivers/postgres/queries.py
supabase_pydantic/db/exceptions.py
supabase_pydantic/db/factories/__init__.py
supabase_pydantic/db/factories/connection_factory.py
supabase_pydantic/db/factory.py
supabase_pydantic/db/graph.py
supabase_pydantic/db/marshalers/__init__.py
supabase_pydantic-0.26.9.dist-info/LICENSE
supabase_pydantic-0.26.9.dist-info/METADATA
supabase_pydantic-0.26.9.dist-info/WHEEL
supabase_pydantic-0.26.9.dist-info/entry_points.txt
supabase_pydantic-0.26.9.dist-info/RECORD
