Metadata-Version: 2.1
Name: supabase-pydantic
Version: 0.26.9
Summary: A Pydantic(+) model generator for Supabase
Home-page: https://kmbhm1.github.io/supabase-pydantic
License: MIT
Keywords: supabase,pydantic,fastapi,sqlalchemy,REST,generator,schema,model
Author: K Boehm
Author-email: kmbhm1@gmail.com
Requires-Python: >=3.10,<3.14
Classifier: Development Status :: 3 - Alpha
Classifier: Environment :: Console
Classifier: Framework :: FastAPI
Classifier: Framework :: Pydantic
Classifier: Framework :: Pydantic :: 2
Classifier: Framework :: Pytest
Classifier: Intended Audience :: Developers
Classifier: License :: OSI Approved :: MIT License
Classifier: Natural Language :: English
Classifier: Operating System :: MacOS :: MacOS X
Classifier: Programming Language :: PL/SQL
Classifier: Programming Language :: Python
Classifier: Programming Language :: Python :: 3
Classifier: Programming Language :: Python :: 3.10
Classifier: Programming Language :: Python :: 3.11
Classifier: Programming Language :: Python :: 3.12
Classifier: Programming Language :: Python :: 3.13
Requires-Dist: click (>=8.1.7,<9.0.0)
Requires-Dist: click-option-group (>=0.5.6,<0.6.0)
Requires-Dist: faker (>=24.11.0,<25.0.0)
Requires-Dist: inflection (>=0.5.1,<0.6.0)
Requires-Dist: loguru (>=0.7.2,<0.8.0)
Requires-Dist: mysql-connector-python (>=8.0.32,<9.4.0)
Requires-Dist: psycopg2-binary (>=2.9.9,<3.0.0)
Requires-Dist: pydantic (>=2.6.3,<3.0.0)
Requires-Dist: python-dotenv (>=1.0.1,<2.0.0)
Requires-Dist: requests (>=2.32.4)
Requires-Dist: toml (>=0.10.2,<0.11.0)
Requires-Dist: types-psycopg2 (>=2.9.21.20240417,<3.0.0.0)
Requires-Dist: urllib3 (>=2.6.0,<3.0.0)
Project-URL: Repository, https://github.com/kmbhm1/supabase-pydantic
